{
  "type": "Program",
  "start": 0,
  "end": 585,
  "loc": {
    "start": {
      "line": 1,
      "column": 0
    },
    "end": {
      "line": 34,
      "column": 0
    }
  },
  "sourceType": "module",
  "body": [
    {
      "type": "ExpressionStatement",
      "start": 0,
      "end": 12,
      "loc": {
        "start": {
          "line": 1,
          "column": 0
        },
        "end": {
          "line": 1,
          "column": 12
        }
      },
      "expression": {
        "type": "Literal",
        "start": 0,
        "end": 12,
        "loc": {
          "start": {
            "line": 1,
            "column": 0
          },
          "end": {
            "line": 1,
            "column": 12
          }
        },
        "value": "use strict",
        "rawValue": "use strict",
        "raw": "'use strict'",
        "leadingComments": null,
        "trailingComments": null
      },
      "trailingComments": [
        {
          "type": "Block",
          "value": "*\n * Module dependencies.\n ",
          "start": 14,
          "end": 45,
          "loc": {
            "start": {
              "line": 3,
              "column": 0
            },
            "end": {
              "line": 5,
              "column": 3
            }
          },
          "range": [
            14,
            45
          ]
        }
      ]
    },
    {
      "type": "ImportDeclaration",
      "start": 47,
      "end": 96,
      "loc": {
        "start": {
          "line": 7,
          "column": 0
        },
        "end": {
          "line": 7,
          "column": 49
        }
      },
      "specifiers": [
        {
          "type": "ImportSpecifier",
          "start": 56,
          "end": 69,
          "loc": {
            "start": {
              "line": 7,
              "column": 9
            },
            "end": {
              "line": 7,
              "column": 22
            }
          },
          "imported": {
            "type": "Identifier",
            "start": 56,
            "end": 69,
            "loc": {
              "start": {
                "line": 7,
                "column": 9
              },
              "end": {
                "line": 7,
                "column": 22
              }
            },
            "name": "PlaneGeometry",
            "leadingComments": null
          },
          "local": {
            "type": "Identifier",
            "start": 56,
            "end": 69,
            "loc": {
              "start": {
                "line": 7,
                "column": 9
              },
              "end": {
                "line": 7,
                "column": 22
              }
            },
            "name": "PlaneGeometry",
            "leadingComments": [
              {
                "type": "Block",
                "value": "*\n * Module dependencies.\n ",
                "start": 14,
                "end": 45,
                "loc": {
                  "start": {
                    "line": 3,
                    "column": 0
                  },
                  "end": {
                    "line": 5,
                    "column": 3
                  }
                },
                "range": [
                  14,
                  45
                ]
              }
            ]
          },
          "leadingComments": null
        }
      ],
      "importKind": "value",
      "source": {
        "type": "Literal",
        "start": 77,
        "end": 96,
        "loc": {
          "start": {
            "line": 7,
            "column": 30
          },
          "end": {
            "line": 7,
            "column": 49
          }
        },
        "value": "../geometry/plane",
        "rawValue": "../geometry/plane",
        "raw": "'../geometry/plane'"
      },
      "leadingComments": [
        {
          "type": "Block",
          "value": "*\n * Module dependencies.\n ",
          "start": 14,
          "end": 45,
          "loc": {
            "start": {
              "line": 3,
              "column": 0
            },
            "end": {
              "line": 5,
              "column": 3
            }
          },
          "range": [
            14,
            45
          ]
        }
      ]
    },
    {
      "type": "ImportDeclaration",
      "start": 97,
      "end": 133,
      "loc": {
        "start": {
          "line": 8,
          "column": 0
        },
        "end": {
          "line": 8,
          "column": 36
        }
      },
      "specifiers": [
        {
          "type": "ImportSpecifier",
          "start": 106,
          "end": 117,
          "loc": {
            "start": {
              "line": 8,
              "column": 9
            },
            "end": {
              "line": 8,
              "column": 20
            }
          },
          "imported": {
            "type": "Identifier",
            "start": 106,
            "end": 117,
            "loc": {
              "start": {
                "line": 8,
                "column": 9
              },
              "end": {
                "line": 8,
                "column": 20
              }
            },
            "name": "MeshCommand"
          },
          "local": {
            "type": "Identifier",
            "start": 106,
            "end": 117,
            "loc": {
              "start": {
                "line": 8,
                "column": 9
              },
              "end": {
                "line": 8,
                "column": 20
              }
            },
            "name": "MeshCommand"
          }
        }
      ],
      "importKind": "value",
      "source": {
        "type": "Literal",
        "start": 125,
        "end": 133,
        "loc": {
          "start": {
            "line": 8,
            "column": 28
          },
          "end": {
            "line": 8,
            "column": 36
          }
        },
        "value": "./mesh",
        "rawValue": "./mesh",
        "raw": "'./mesh'"
      }
    },
    {
      "type": "ImportDeclaration",
      "start": 134,
      "end": 160,
      "loc": {
        "start": {
          "line": 9,
          "column": 0
        },
        "end": {
          "line": 9,
          "column": 26
        }
      },
      "specifiers": [
        {
          "type": "ImportDefaultSpecifier",
          "start": 141,
          "end": 145,
          "loc": {
            "start": {
              "line": 9,
              "column": 7
            },
            "end": {
              "line": 9,
              "column": 11
            }
          },
          "local": {
            "type": "Identifier",
            "start": 141,
            "end": 145,
            "loc": {
              "start": {
                "line": 9,
                "column": 7
              },
              "end": {
                "line": 9,
                "column": 11
              }
            },
            "name": "mat4"
          }
        }
      ],
      "importKind": "value",
      "source": {
        "type": "Literal",
        "start": 151,
        "end": 160,
        "loc": {
          "start": {
            "line": 9,
            "column": 17
          },
          "end": {
            "line": 9,
            "column": 26
          }
        },
        "value": "gl-mat4",
        "rawValue": "gl-mat4",
        "raw": "'gl-mat4'"
      }
    },
    {
      "type": "ImportDeclaration",
      "start": 161,
      "end": 187,
      "loc": {
        "start": {
          "line": 10,
          "column": 0
        },
        "end": {
          "line": 10,
          "column": 26
        }
      },
      "specifiers": [
        {
          "type": "ImportDefaultSpecifier",
          "start": 168,
          "end": 172,
          "loc": {
            "start": {
              "line": 10,
              "column": 7
            },
            "end": {
              "line": 10,
              "column": 11
            }
          },
          "local": {
            "type": "Identifier",
            "start": 168,
            "end": 172,
            "loc": {
              "start": {
                "line": 10,
                "column": 7
              },
              "end": {
                "line": 10,
                "column": 11
              }
            },
            "name": "glsl"
          }
        }
      ],
      "importKind": "value",
      "source": {
        "type": "Literal",
        "start": 178,
        "end": 187,
        "loc": {
          "start": {
            "line": 10,
            "column": 17
          },
          "end": {
            "line": 10,
            "column": 26
          }
        },
        "value": "glslify",
        "rawValue": "glslify",
        "raw": "'glslify'",
        "leadingComments": null,
        "trailingComments": null
      },
      "trailingComments": [
        {
          "type": "Block",
          "value": "*\n * Plane function.\n *\n * @see PlaneCommand\n ",
          "start": 189,
          "end": 239,
          "loc": {
            "start": {
              "line": 12,
              "column": 0
            },
            "end": {
              "line": 16,
              "column": 3
            }
          },
          "range": [
            189,
            239
          ]
        }
      ]
    },
    {
      "type": "ExpressionStatement",
      "start": 241,
      "end": 306,
      "loc": {
        "start": {
          "line": 18,
          "column": 0
        },
        "end": {
          "line": 18,
          "column": 65
        }
      },
      "expression": {
        "type": "AssignmentExpression",
        "start": 241,
        "end": 306,
        "loc": {
          "start": {
            "line": 18,
            "column": 0
          },
          "end": {
            "line": 18,
            "column": 65
          }
        },
        "operator": "=",
        "left": {
          "type": "MemberExpression",
          "start": 241,
          "end": 255,
          "loc": {
            "start": {
              "line": 18,
              "column": 0
            },
            "end": {
              "line": 18,
              "column": 14
            }
          },
          "object": {
            "type": "Identifier",
            "start": 241,
            "end": 247,
            "loc": {
              "start": {
                "line": 18,
                "column": 0
              },
              "end": {
                "line": 18,
                "column": 6
              }
            },
            "name": "module",
            "leadingComments": null
          },
          "property": {
            "type": "Identifier",
            "start": 248,
            "end": 255,
            "loc": {
              "start": {
                "line": 18,
                "column": 7
              },
              "end": {
                "line": 18,
                "column": 14
              }
            },
            "name": "exports"
          },
          "computed": false,
          "leadingComments": null
        },
        "right": {
          "type": "AssignmentExpression",
          "start": 258,
          "end": 306,
          "loc": {
            "start": {
              "line": 18,
              "column": 17
            },
            "end": {
              "line": 18,
              "column": 65
            }
          },
          "operator": "=",
          "left": {
            "type": "Identifier",
            "start": 258,
            "end": 265,
            "loc": {
              "start": {
                "line": 18,
                "column": 17
              },
              "end": {
                "line": 18,
                "column": 24
              }
            },
            "name": "exports"
          },
          "right": {
            "type": "ArrowFunctionExpression",
            "start": 268,
            "end": 306,
            "loc": {
              "start": {
                "line": 18,
                "column": 27
              },
              "end": {
                "line": 18,
                "column": 65
              }
            },
            "id": null,
            "generator": false,
            "expression": true,
            "async": false,
            "params": [
              {
                "type": "RestElement",
                "start": 269,
                "end": 276,
                "loc": {
                  "start": {
                    "line": 18,
                    "column": 28
                  },
                  "end": {
                    "line": 18,
                    "column": 35
                  }
                },
                "argument": {
                  "type": "Identifier",
                  "start": 272,
                  "end": 276,
                  "loc": {
                    "start": {
                      "line": 18,
                      "column": 31
                    },
                    "end": {
                      "line": 18,
                      "column": 35
                    }
                  },
                  "name": "args"
                }
              }
            ],
            "body": {
              "type": "NewExpression",
              "start": 281,
              "end": 306,
              "loc": {
                "start": {
                  "line": 18,
                  "column": 40
                },
                "end": {
                  "line": 18,
                  "column": 65
                }
              },
              "callee": {
                "type": "Identifier",
                "start": 285,
                "end": 297,
                "loc": {
                  "start": {
                    "line": 18,
                    "column": 44
                  },
                  "end": {
                    "line": 18,
                    "column": 56
                  }
                },
                "name": "PlaneCommand"
              },
              "arguments": [
                {
                  "type": "SpreadElement",
                  "start": 298,
                  "end": 305,
                  "loc": {
                    "start": {
                      "line": 18,
                      "column": 57
                    },
                    "end": {
                      "line": 18,
                      "column": 64
                    }
                  },
                  "argument": {
                    "type": "Identifier",
                    "start": 301,
                    "end": 305,
                    "loc": {
                      "start": {
                        "line": 18,
                        "column": 60
                      },
                      "end": {
                        "line": 18,
                        "column": 64
                      }
                    },
                    "name": "args"
                  }
                }
              ],
              "trailingComments": null
            },
            "trailingComments": null
          },
          "trailingComments": null
        },
        "leadingComments": null,
        "trailingComments": null
      },
      "leadingComments": [
        {
          "type": "Block",
          "value": "*\n * Plane function.\n *\n * @see PlaneCommand\n ",
          "start": 189,
          "end": 239,
          "loc": {
            "start": {
              "line": 12,
              "column": 0
            },
            "end": {
              "line": 16,
              "column": 3
            }
          },
          "range": [
            189,
            239
          ]
        }
      ],
      "trailingComments": [
        {
          "type": "Block",
          "value": "*\n * PlaneCommand class.\n *\n * @public\n * @class PlaneCommand\n * @extends MeshCommand\n ",
          "start": 308,
          "end": 399,
          "loc": {
            "start": {
              "line": 20,
              "column": 0
            },
            "end": {
              "line": 26,
              "column": 3
            }
          },
          "range": [
            308,
            399
          ]
        }
      ]
    },
    {
      "type": "ExportNamedDeclaration",
      "start": 401,
      "end": 584,
      "loc": {
        "start": {
          "line": 28,
          "column": 0
        },
        "end": {
          "line": 33,
          "column": 1
        }
      },
      "declaration": {
        "type": "ClassDeclaration",
        "start": 408,
        "end": 584,
        "loc": {
          "start": {
            "line": 28,
            "column": 7
          },
          "end": {
            "line": 33,
            "column": 1
          }
        },
        "id": {
          "type": "Identifier",
          "start": 414,
          "end": 426,
          "loc": {
            "start": {
              "line": 28,
              "column": 13
            },
            "end": {
              "line": 28,
              "column": 25
            }
          },
          "name": "PlaneCommand",
          "leadingComments": null
        },
        "superClass": {
          "type": "Identifier",
          "start": 435,
          "end": 446,
          "loc": {
            "start": {
              "line": 28,
              "column": 34
            },
            "end": {
              "line": 28,
              "column": 45
            }
          },
          "name": "MeshCommand"
        },
        "body": {
          "type": "ClassBody",
          "start": 447,
          "end": 584,
          "loc": {
            "start": {
              "line": 28,
              "column": 46
            },
            "end": {
              "line": 33,
              "column": 1
            }
          },
          "body": [
            {
              "type": "MethodDefinition",
              "start": 451,
              "end": 582,
              "loc": {
                "start": {
                  "line": 29,
                  "column": 2
                },
                "end": {
                  "line": 32,
                  "column": 3
                }
              },
              "computed": false,
              "key": {
                "type": "Identifier",
                "start": 451,
                "end": 462,
                "loc": {
                  "start": {
                    "line": 29,
                    "column": 2
                  },
                  "end": {
                    "line": 29,
                    "column": 13
                  }
                },
                "name": "constructor"
              },
              "static": false,
              "kind": "constructor",
              "value": {
                "type": "FunctionExpression",
                "start": 462,
                "end": 582,
                "loc": {
                  "start": {
                    "line": 29,
                    "column": 13
                  },
                  "end": {
                    "line": 32,
                    "column": 3
                  }
                },
                "id": null,
                "generator": false,
                "expression": false,
                "async": false,
                "params": [
                  {
                    "type": "Identifier",
                    "start": 463,
                    "end": 466,
                    "loc": {
                      "start": {
                        "line": 29,
                        "column": 14
                      },
                      "end": {
                        "line": 29,
                        "column": 17
                      }
                    },
                    "name": "ctx"
                  },
                  {
                    "type": "AssignmentPattern",
                    "start": 468,
                    "end": 477,
                    "loc": {
                      "start": {
                        "line": 29,
                        "column": 19
                      },
                      "end": {
                        "line": 29,
                        "column": 28
                      }
                    },
                    "operator": "=",
                    "left": {
                      "type": "Identifier",
                      "start": 468,
                      "end": 472,
                      "loc": {
                        "start": {
                          "line": 29,
                          "column": 19
                        },
                        "end": {
                          "line": 29,
                          "column": 23
                        }
                      },
                      "name": "opts"
                    },
                    "right": {
                      "type": "ObjectExpression",
                      "start": 475,
                      "end": 477,
                      "loc": {
                        "start": {
                          "line": 29,
                          "column": 26
                        },
                        "end": {
                          "line": 29,
                          "column": 28
                        }
                      },
                      "properties": []
                    }
                  }
                ],
                "body": {
                  "type": "BlockStatement",
                  "start": 479,
                  "end": 582,
                  "loc": {
                    "start": {
                      "line": 29,
                      "column": 30
                    },
                    "end": {
                      "line": 32,
                      "column": 3
                    }
                  },
                  "body": [
                    {
                      "type": "VariableDeclaration",
                      "start": 485,
                      "end": 525,
                      "loc": {
                        "start": {
                          "line": 30,
                          "column": 4
                        },
                        "end": {
                          "line": 30,
                          "column": 44
                        }
                      },
                      "declarations": [
                        {
                          "type": "VariableDeclarator",
                          "start": 491,
                          "end": 525,
                          "loc": {
                            "start": {
                              "line": 30,
                              "column": 10
                            },
                            "end": {
                              "line": 30,
                              "column": 44
                            }
                          },
                          "id": {
                            "type": "Identifier",
                            "start": 491,
                            "end": 499,
                            "loc": {
                              "start": {
                                "line": 30,
                                "column": 10
                              },
                              "end": {
                                "line": 30,
                                "column": 18
                              }
                            },
                            "name": "geometry"
                          },
                          "init": {
                            "type": "NewExpression",
                            "start": 502,
                            "end": 525,
                            "loc": {
                              "start": {
                                "line": 30,
                                "column": 21
                              },
                              "end": {
                                "line": 30,
                                "column": 44
                              }
                            },
                            "callee": {
                              "type": "Identifier",
                              "start": 506,
                              "end": 519,
                              "loc": {
                                "start": {
                                  "line": 30,
                                  "column": 25
                                },
                                "end": {
                                  "line": 30,
                                  "column": 38
                                }
                              },
                              "name": "PlaneGeometry"
                            },
                            "arguments": [
                              {
                                "type": "Identifier",
                                "start": 520,
                                "end": 524,
                                "loc": {
                                  "start": {
                                    "line": 30,
                                    "column": 39
                                  },
                                  "end": {
                                    "line": 30,
                                    "column": 43
                                  }
                                },
                                "name": "opts"
                              }
                            ]
                          }
                        }
                      ],
                      "kind": "const"
                    },
                    {
                      "type": "ExpressionStatement",
                      "start": 530,
                      "end": 578,
                      "loc": {
                        "start": {
                          "line": 31,
                          "column": 4
                        },
                        "end": {
                          "line": 31,
                          "column": 52
                        }
                      },
                      "expression": {
                        "type": "CallExpression",
                        "start": 530,
                        "end": 578,
                        "loc": {
                          "start": {
                            "line": 31,
                            "column": 4
                          },
                          "end": {
                            "line": 31,
                            "column": 52
                          }
                        },
                        "callee": {
                          "type": "Super",
                          "start": 530,
                          "end": 535,
                          "loc": {
                            "start": {
                              "line": 31,
                              "column": 4
                            },
                            "end": {
                              "line": 31,
                              "column": 9
                            }
                          }
                        },
                        "arguments": [
                          {
                            "type": "Identifier",
                            "start": 536,
                            "end": 539,
                            "loc": {
                              "start": {
                                "line": 31,
                                "column": 10
                              },
                              "end": {
                                "line": 31,
                                "column": 13
                              }
                            },
                            "name": "ctx"
                          },
                          {
                            "type": "ObjectExpression",
                            "start": 541,
                            "end": 577,
                            "loc": {
                              "start": {
                                "line": 31,
                                "column": 15
                              },
                              "end": {
                                "line": 31,
                                "column": 51
                              }
                            },
                            "properties": [
                              {
                                "type": "SpreadProperty",
                                "start": 543,
                                "end": 550,
                                "loc": {
                                  "start": {
                                    "line": 31,
                                    "column": 17
                                  },
                                  "end": {
                                    "line": 31,
                                    "column": 24
                                  }
                                },
                                "argument": {
                                  "type": "Identifier",
                                  "start": 546,
                                  "end": 550,
                                  "loc": {
                                    "start": {
                                      "line": 31,
                                      "column": 20
                                    },
                                    "end": {
                                      "line": 31,
                                      "column": 24
                                    }
                                  },
                                  "name": "opts"
                                }
                              },
                              {
                                "type": "Property",
                                "start": 552,
                                "end": 565,
                                "loc": {
                                  "start": {
                                    "line": 31,
                                    "column": 26
                                  },
                                  "end": {
                                    "line": 31,
                                    "column": 39
                                  }
                                },
                                "method": false,
                                "shorthand": false,
                                "computed": false,
                                "key": {
                                  "type": "Identifier",
                                  "start": 552,
                                  "end": 556,
                                  "loc": {
                                    "start": {
                                      "line": 31,
                                      "column": 26
                                    },
                                    "end": {
                                      "line": 31,
                                      "column": 30
                                    }
                                  },
                                  "name": "type"
                                },
                                "value": {
                                  "type": "Literal",
                                  "start": 558,
                                  "end": 565,
                                  "loc": {
                                    "start": {
                                      "line": 31,
                                      "column": 32
                                    },
                                    "end": {
                                      "line": 31,
                                      "column": 39
                                    }
                                  },
                                  "value": "plane",
                                  "rawValue": "plane",
                                  "raw": "'plane'"
                                },
                                "kind": "init"
                              },
                              {
                                "type": "Property",
                                "start": 567,
                                "end": 575,
                                "loc": {
                                  "start": {
                                    "line": 31,
                                    "column": 41
                                  },
                                  "end": {
                                    "line": 31,
                                    "column": 49
                                  }
                                },
                                "method": false,
                                "shorthand": true,
                                "computed": false,
                                "key": {
                                  "type": "Identifier",
                                  "start": 567,
                                  "end": 575,
                                  "loc": {
                                    "start": {
                                      "line": 31,
                                      "column": 41
                                    },
                                    "end": {
                                      "line": 31,
                                      "column": 49
                                    }
                                  },
                                  "name": "geometry"
                                },
                                "kind": "init",
                                "value": {
                                  "type": "Identifier",
                                  "start": 567,
                                  "end": 575,
                                  "loc": {
                                    "start": {
                                      "line": 31,
                                      "column": 41
                                    },
                                    "end": {
                                      "line": 31,
                                      "column": 49
                                    }
                                  },
                                  "name": "geometry"
                                }
                              }
                            ]
                          }
                        ]
                      }
                    }
                  ]
                }
              }
            }
          ]
        },
        "leadingComments": [
          {
            "type": "Block",
            "value": "*\n * PlaneCommand class.\n *\n * @public\n * @class PlaneCommand\n * @extends MeshCommand\n ",
            "start": 308,
            "end": 399,
            "loc": {
              "start": {
                "line": 20,
                "column": 0
              },
              "end": {
                "line": 26,
                "column": 3
              }
            },
            "range": [
              308,
              399
            ]
          }
        ],
        "trailingComments": []
      },
      "specifiers": [],
      "source": null,
      "leadingComments": [
        {
          "type": "Block",
          "value": "*\n * PlaneCommand class.\n *\n * @public\n * @class PlaneCommand\n * @extends MeshCommand\n ",
          "start": 308,
          "end": 399,
          "loc": {
            "start": {
              "line": 20,
              "column": 0
            },
            "end": {
              "line": 26,
              "column": 3
            }
          },
          "range": [
            308,
            399
          ]
        }
      ]
    }
  ]
}