{
  "type": "Program",
  "start": 0,
  "end": 508,
  "loc": {
    "start": {
      "line": 1,
      "column": 0
    },
    "end": {
      "line": 28,
      "column": 0
    }
  },
  "sourceType": "module",
  "body": [
    {
      "type": "ExpressionStatement",
      "start": 0,
      "end": 12,
      "loc": {
        "start": {
          "line": 1,
          "column": 0
        },
        "end": {
          "line": 1,
          "column": 12
        }
      },
      "expression": {
        "type": "Literal",
        "start": 0,
        "end": 12,
        "loc": {
          "start": {
            "line": 1,
            "column": 0
          },
          "end": {
            "line": 1,
            "column": 12
          }
        },
        "value": "use strict",
        "rawValue": "use strict",
        "raw": "'use strict'",
        "leadingComments": null,
        "trailingComments": null
      },
      "trailingComments": [
        {
          "type": "Block",
          "value": "*\n * Module dependencies.\n ",
          "start": 14,
          "end": 45,
          "loc": {
            "start": {
              "line": 3,
              "column": 0
            },
            "end": {
              "line": 5,
              "column": 3
            }
          },
          "range": [
            14,
            45
          ]
        }
      ]
    },
    {
      "type": "ImportDeclaration",
      "start": 47,
      "end": 84,
      "loc": {
        "start": {
          "line": 7,
          "column": 0
        },
        "end": {
          "line": 7,
          "column": 37
        }
      },
      "specifiers": [
        {
          "type": "ImportSpecifier",
          "start": 56,
          "end": 63,
          "loc": {
            "start": {
              "line": 7,
              "column": 9
            },
            "end": {
              "line": 7,
              "column": 16
            }
          },
          "imported": {
            "type": "Identifier",
            "start": 56,
            "end": 63,
            "loc": {
              "start": {
                "line": 7,
                "column": 9
              },
              "end": {
                "line": 7,
                "column": 16
              }
            },
            "name": "radians",
            "leadingComments": null
          },
          "local": {
            "type": "Identifier",
            "start": 56,
            "end": 63,
            "loc": {
              "start": {
                "line": 7,
                "column": 9
              },
              "end": {
                "line": 7,
                "column": 16
              }
            },
            "name": "radians",
            "leadingComments": [
              {
                "type": "Block",
                "value": "*\n * Module dependencies.\n ",
                "start": 14,
                "end": 45,
                "loc": {
                  "start": {
                    "line": 3,
                    "column": 0
                  },
                  "end": {
                    "line": 5,
                    "column": 3
                  }
                },
                "range": [
                  14,
                  45
                ]
              }
            ]
          },
          "leadingComments": null
        }
      ],
      "importKind": "value",
      "source": {
        "type": "Literal",
        "start": 71,
        "end": 84,
        "loc": {
          "start": {
            "line": 7,
            "column": 24
          },
          "end": {
            "line": 7,
            "column": 37
          }
        },
        "value": "../../utils",
        "rawValue": "../../utils",
        "raw": "'../../utils'"
      },
      "leadingComments": [
        {
          "type": "Block",
          "value": "*\n * Module dependencies.\n ",
          "start": 14,
          "end": 45,
          "loc": {
            "start": {
              "line": 3,
              "column": 0
            },
            "end": {
              "line": 5,
              "column": 3
            }
          },
          "range": [
            14,
            45
          ]
        }
      ]
    },
    {
      "type": "ImportDeclaration",
      "start": 85,
      "end": 110,
      "loc": {
        "start": {
          "line": 8,
          "column": 0
        },
        "end": {
          "line": 8,
          "column": 25
        }
      },
      "specifiers": [
        {
          "type": "ImportDefaultSpecifier",
          "start": 92,
          "end": 97,
          "loc": {
            "start": {
              "line": 8,
              "column": 7
            },
            "end": {
              "line": 8,
              "column": 12
            }
          },
          "local": {
            "type": "Identifier",
            "start": 92,
            "end": 97,
            "loc": {
              "start": {
                "line": 8,
                "column": 7
              },
              "end": {
                "line": 8,
                "column": 12
              }
            },
            "name": "clamp"
          }
        }
      ],
      "importKind": "value",
      "source": {
        "type": "Literal",
        "start": 103,
        "end": 110,
        "loc": {
          "start": {
            "line": 8,
            "column": 18
          },
          "end": {
            "line": 8,
            "column": 25
          }
        },
        "value": "clamp",
        "rawValue": "clamp",
        "raw": "'clamp'"
      }
    },
    {
      "type": "ExpressionStatement",
      "start": 112,
      "end": 507,
      "loc": {
        "start": {
          "line": 10,
          "column": 0
        },
        "end": {
          "line": 27,
          "column": 1
        }
      },
      "expression": {
        "type": "AssignmentExpression",
        "start": 112,
        "end": 507,
        "loc": {
          "start": {
            "line": 10,
            "column": 0
          },
          "end": {
            "line": 27,
            "column": 1
          }
        },
        "operator": "=",
        "left": {
          "type": "MemberExpression",
          "start": 112,
          "end": 126,
          "loc": {
            "start": {
              "line": 10,
              "column": 0
            },
            "end": {
              "line": 10,
              "column": 14
            }
          },
          "object": {
            "type": "Identifier",
            "start": 112,
            "end": 118,
            "loc": {
              "start": {
                "line": 10,
                "column": 0
              },
              "end": {
                "line": 10,
                "column": 6
              }
            },
            "name": "module"
          },
          "property": {
            "type": "Identifier",
            "start": 119,
            "end": 126,
            "loc": {
              "start": {
                "line": 10,
                "column": 7
              },
              "end": {
                "line": 10,
                "column": 14
              }
            },
            "name": "exports"
          },
          "computed": false
        },
        "right": {
          "type": "AssignmentExpression",
          "start": 129,
          "end": 507,
          "loc": {
            "start": {
              "line": 10,
              "column": 17
            },
            "end": {
              "line": 27,
              "column": 1
            }
          },
          "operator": "=",
          "left": {
            "type": "Identifier",
            "start": 129,
            "end": 136,
            "loc": {
              "start": {
                "line": 10,
                "column": 17
              },
              "end": {
                "line": 10,
                "column": 24
              }
            },
            "name": "exports"
          },
          "right": {
            "type": "ArrowFunctionExpression",
            "start": 139,
            "end": 507,
            "loc": {
              "start": {
                "line": 10,
                "column": 27
              },
              "end": {
                "line": 27,
                "column": 1
              }
            },
            "id": null,
            "generator": false,
            "expression": false,
            "async": false,
            "params": [
              {
                "type": "AssignmentPattern",
                "start": 140,
                "end": 220,
                "loc": {
                  "start": {
                    "line": 10,
                    "column": 28
                  },
                  "end": {
                    "line": 15,
                    "column": 6
                  }
                },
                "left": {
                  "type": "ObjectPattern",
                  "start": 140,
                  "end": 215,
                  "loc": {
                    "start": {
                      "line": 10,
                      "column": 28
                    },
                    "end": {
                      "line": 15,
                      "column": 1
                    }
                  },
                  "properties": [
                    {
                      "type": "Property",
                      "start": 144,
                      "end": 161,
                      "loc": {
                        "start": {
                          "line": 11,
                          "column": 2
                        },
                        "end": {
                          "line": 11,
                          "column": 19
                        }
                      },
                      "method": false,
                      "shorthand": false,
                      "computed": false,
                      "key": {
                        "type": "Identifier",
                        "start": 144,
                        "end": 154,
                        "loc": {
                          "start": {
                            "line": 11,
                            "column": 2
                          },
                          "end": {
                            "line": 11,
                            "column": 12
                          }
                        },
                        "name": "touchInput"
                      },
                      "value": {
                        "type": "Identifier",
                        "start": 156,
                        "end": 161,
                        "loc": {
                          "start": {
                            "line": 11,
                            "column": 14
                          },
                          "end": {
                            "line": 11,
                            "column": 19
                          }
                        },
                        "name": "touch"
                      },
                      "kind": "init"
                    },
                    {
                      "type": "Property",
                      "start": 165,
                      "end": 176,
                      "loc": {
                        "start": {
                          "line": 12,
                          "column": 2
                        },
                        "end": {
                          "line": 12,
                          "column": 13
                        }
                      },
                      "method": false,
                      "shorthand": true,
                      "computed": false,
                      "key": {
                        "type": "Identifier",
                        "start": 165,
                        "end": 176,
                        "loc": {
                          "start": {
                            "line": 12,
                            "column": 2
                          },
                          "end": {
                            "line": 12,
                            "column": 13
                          }
                        },
                        "name": "orientation"
                      },
                      "kind": "init",
                      "value": {
                        "type": "Identifier",
                        "start": 165,
                        "end": 176,
                        "loc": {
                          "start": {
                            "line": 12,
                            "column": 2
                          },
                          "end": {
                            "line": 12,
                            "column": 13
                          }
                        },
                        "name": "orientation"
                      }
                    },
                    {
                      "type": "Property",
                      "start": 180,
                      "end": 192,
                      "loc": {
                        "start": {
                          "line": 13,
                          "column": 2
                        },
                        "end": {
                          "line": 13,
                          "column": 14
                        }
                      },
                      "method": false,
                      "shorthand": true,
                      "computed": false,
                      "key": {
                        "type": "Identifier",
                        "start": 180,
                        "end": 188,
                        "loc": {
                          "start": {
                            "line": 13,
                            "column": 2
                          },
                          "end": {
                            "line": 13,
                            "column": 10
                          }
                        },
                        "name": "friction"
                      },
                      "kind": "init",
                      "value": {
                        "type": "AssignmentPattern",
                        "start": 180,
                        "end": 192,
                        "loc": {
                          "start": {
                            "line": 13,
                            "column": 2
                          },
                          "end": {
                            "line": 13,
                            "column": 14
                          }
                        },
                        "operator": "=",
                        "left": {
                          "type": "Identifier",
                          "start": 180,
                          "end": 188,
                          "loc": {
                            "start": {
                              "line": 13,
                              "column": 2
                            },
                            "end": {
                              "line": 13,
                              "column": 10
                            }
                          },
                          "name": "friction"
                        },
                        "right": {
                          "type": "Literal",
                          "start": 191,
                          "end": 192,
                          "loc": {
                            "start": {
                              "line": 13,
                              "column": 13
                            },
                            "end": {
                              "line": 13,
                              "column": 14
                            }
                          },
                          "value": 1,
                          "rawValue": 1,
                          "raw": "1"
                        }
                      }
                    },
                    {
                      "type": "Property",
                      "start": 198,
                      "end": 212,
                      "loc": {
                        "start": {
                          "line": 14,
                          "column": 4
                        },
                        "end": {
                          "line": 14,
                          "column": 18
                        }
                      },
                      "method": false,
                      "shorthand": true,
                      "computed": false,
                      "key": {
                        "type": "Identifier",
                        "start": 198,
                        "end": 204,
                        "loc": {
                          "start": {
                            "line": 14,
                            "column": 4
                          },
                          "end": {
                            "line": 14,
                            "column": 10
                          }
                        },
                        "name": "invert"
                      },
                      "kind": "init",
                      "value": {
                        "type": "AssignmentPattern",
                        "start": 198,
                        "end": 212,
                        "loc": {
                          "start": {
                            "line": 14,
                            "column": 4
                          },
                          "end": {
                            "line": 14,
                            "column": 18
                          }
                        },
                        "operator": "=",
                        "left": {
                          "type": "Identifier",
                          "start": 198,
                          "end": 204,
                          "loc": {
                            "start": {
                              "line": 14,
                              "column": 4
                            },
                            "end": {
                              "line": 14,
                              "column": 10
                            }
                          },
                          "name": "invert"
                        },
                        "right": {
                          "type": "Literal",
                          "start": 207,
                          "end": 212,
                          "loc": {
                            "start": {
                              "line": 14,
                              "column": 13
                            },
                            "end": {
                              "line": 14,
                              "column": 18
                            }
                          },
                          "value": false,
                          "rawValue": false,
                          "raw": "false"
                        }
                      }
                    }
                  ]
                },
                "right": {
                  "type": "ObjectExpression",
                  "start": 218,
                  "end": 220,
                  "loc": {
                    "start": {
                      "line": 15,
                      "column": 4
                    },
                    "end": {
                      "line": 15,
                      "column": 6
                    }
                  },
                  "properties": []
                }
              }
            ],
            "body": {
              "type": "BlockStatement",
              "start": 225,
              "end": 507,
              "loc": {
                "start": {
                  "line": 15,
                  "column": 11
                },
                "end": {
                  "line": 27,
                  "column": 1
                }
              },
              "body": [
                {
                  "type": "ExpressionStatement",
                  "start": 229,
                  "end": 505,
                  "loc": {
                    "start": {
                      "line": 16,
                      "column": 2
                    },
                    "end": {
                      "line": 26,
                      "column": 4
                    }
                  },
                  "expression": {
                    "type": "CallExpression",
                    "start": 229,
                    "end": 505,
                    "loc": {
                      "start": {
                        "line": 16,
                        "column": 2
                      },
                      "end": {
                        "line": 26,
                        "column": 4
                      }
                    },
                    "callee": {
                      "type": "Identifier",
                      "start": 229,
                      "end": 234,
                      "loc": {
                        "start": {
                          "line": 16,
                          "column": 2
                        },
                        "end": {
                          "line": 16,
                          "column": 7
                        }
                      },
                      "name": "touch"
                    },
                    "arguments": [
                      {
                        "type": "ArrowFunctionExpression",
                        "start": 235,
                        "end": 504,
                        "loc": {
                          "start": {
                            "line": 16,
                            "column": 8
                          },
                          "end": {
                            "line": 26,
                            "column": 3
                          }
                        },
                        "id": null,
                        "generator": false,
                        "expression": false,
                        "async": false,
                        "params": [
                          {
                            "type": "ObjectPattern",
                            "start": 236,
                            "end": 287,
                            "loc": {
                              "start": {
                                "line": 16,
                                "column": 9
                              },
                              "end": {
                                "line": 20,
                                "column": 3
                              }
                            },
                            "properties": [
                              {
                                "type": "Property",
                                "start": 242,
                                "end": 250,
                                "loc": {
                                  "start": {
                                    "line": 17,
                                    "column": 4
                                  },
                                  "end": {
                                    "line": 17,
                                    "column": 12
                                  }
                                },
                                "method": false,
                                "shorthand": true,
                                "computed": false,
                                "key": {
                                  "type": "Identifier",
                                  "start": 242,
                                  "end": 250,
                                  "loc": {
                                    "start": {
                                      "line": 17,
                                      "column": 4
                                    },
                                    "end": {
                                      "line": 17,
                                      "column": 12
                                    }
                                  },
                                  "name": "hasTouch"
                                },
                                "kind": "init",
                                "value": {
                                  "type": "Identifier",
                                  "start": 242,
                                  "end": 250,
                                  "loc": {
                                    "start": {
                                      "line": 17,
                                      "column": 4
                                    },
                                    "end": {
                                      "line": 17,
                                      "column": 12
                                    }
                                  },
                                  "name": "hasTouch"
                                }
                              },
                              {
                                "type": "Property",
                                "start": 256,
                                "end": 266,
                                "loc": {
                                  "start": {
                                    "line": 18,
                                    "column": 4
                                  },
                                  "end": {
                                    "line": 18,
                                    "column": 14
                                  }
                                },
                                "method": false,
                                "shorthand": false,
                                "computed": false,
                                "key": {
                                  "type": "Identifier",
                                  "start": 256,
                                  "end": 262,
                                  "loc": {
                                    "start": {
                                      "line": 18,
                                      "column": 4
                                    },
                                    "end": {
                                      "line": 18,
                                      "column": 10
                                    }
                                  },
                                  "name": "deltaX"
                                },
                                "value": {
                                  "type": "Identifier",
                                  "start": 264,
                                  "end": 266,
                                  "loc": {
                                    "start": {
                                      "line": 18,
                                      "column": 12
                                    },
                                    "end": {
                                      "line": 18,
                                      "column": 14
                                    }
                                  },
                                  "name": "dx"
                                },
                                "kind": "init"
                              },
                              {
                                "type": "Property",
                                "start": 272,
                                "end": 282,
                                "loc": {
                                  "start": {
                                    "line": 19,
                                    "column": 4
                                  },
                                  "end": {
                                    "line": 19,
                                    "column": 14
                                  }
                                },
                                "method": false,
                                "shorthand": false,
                                "computed": false,
                                "key": {
                                  "type": "Identifier",
                                  "start": 272,
                                  "end": 278,
                                  "loc": {
                                    "start": {
                                      "line": 19,
                                      "column": 4
                                    },
                                    "end": {
                                      "line": 19,
                                      "column": 10
                                    }
                                  },
                                  "name": "deltaY"
                                },
                                "value": {
                                  "type": "Identifier",
                                  "start": 280,
                                  "end": 282,
                                  "loc": {
                                    "start": {
                                      "line": 19,
                                      "column": 12
                                    },
                                    "end": {
                                      "line": 19,
                                      "column": 14
                                    }
                                  },
                                  "name": "dy"
                                },
                                "kind": "init"
                              }
                            ]
                          }
                        ],
                        "body": {
                          "type": "BlockStatement",
                          "start": 292,
                          "end": 504,
                          "loc": {
                            "start": {
                              "line": 20,
                              "column": 8
                            },
                            "end": {
                              "line": 26,
                              "column": 3
                            }
                          },
                          "body": [
                            {
                              "type": "VariableDeclaration",
                              "start": 298,
                              "end": 313,
                              "loc": {
                                "start": {
                                  "line": 21,
                                  "column": 4
                                },
                                "end": {
                                  "line": 21,
                                  "column": 19
                                }
                              },
                              "declarations": [
                                {
                                  "type": "VariableDeclarator",
                                  "start": 304,
                                  "end": 313,
                                  "loc": {
                                    "start": {
                                      "line": 21,
                                      "column": 10
                                    },
                                    "end": {
                                      "line": 21,
                                      "column": 19
                                    }
                                  },
                                  "id": {
                                    "type": "Identifier",
                                    "start": 304,
                                    "end": 305,
                                    "loc": {
                                      "start": {
                                        "line": 21,
                                        "column": 10
                                      },
                                      "end": {
                                        "line": 21,
                                        "column": 11
                                      }
                                    },
                                    "name": "z"
                                  },
                                  "init": {
                                    "type": "Literal",
                                    "start": 308,
                                    "end": 313,
                                    "loc": {
                                      "start": {
                                        "line": 21,
                                        "column": 14
                                      },
                                      "end": {
                                        "line": 21,
                                        "column": 19
                                      }
                                    },
                                    "value": 0.003,
                                    "rawValue": 0.003,
                                    "raw": "0.003"
                                  }
                                }
                              ],
                              "kind": "const"
                            },
                            {
                              "type": "IfStatement",
                              "start": 318,
                              "end": 500,
                              "loc": {
                                "start": {
                                  "line": 22,
                                  "column": 4
                                },
                                "end": {
                                  "line": 25,
                                  "column": 5
                                }
                              },
                              "test": {
                                "type": "Identifier",
                                "start": 322,
                                "end": 330,
                                "loc": {
                                  "start": {
                                    "line": 22,
                                    "column": 8
                                  },
                                  "end": {
                                    "line": 22,
                                    "column": 16
                                  }
                                },
                                "name": "hasTouch"
                              },
                              "consequent": {
                                "type": "BlockStatement",
                                "start": 332,
                                "end": 500,
                                "loc": {
                                  "start": {
                                    "line": 22,
                                    "column": 18
                                  },
                                  "end": {
                                    "line": 25,
                                    "column": 5
                                  }
                                },
                                "body": [
                                  {
                                    "type": "ExpressionStatement",
                                    "start": 340,
                                    "end": 417,
                                    "loc": {
                                      "start": {
                                        "line": 23,
                                        "column": 6
                                      },
                                      "end": {
                                        "line": 23,
                                        "column": 83
                                      }
                                    },
                                    "expression": {
                                      "type": "AssignmentExpression",
                                      "start": 340,
                                      "end": 417,
                                      "loc": {
                                        "start": {
                                          "line": 23,
                                          "column": 6
                                        },
                                        "end": {
                                          "line": 23,
                                          "column": 83
                                        }
                                      },
                                      "operator": "+=",
                                      "left": {
                                        "type": "MemberExpression",
                                        "start": 340,
                                        "end": 354,
                                        "loc": {
                                          "start": {
                                            "line": 23,
                                            "column": 6
                                          },
                                          "end": {
                                            "line": 23,
                                            "column": 20
                                          }
                                        },
                                        "object": {
                                          "type": "Identifier",
                                          "start": 340,
                                          "end": 351,
                                          "loc": {
                                            "start": {
                                              "line": 23,
                                              "column": 6
                                            },
                                            "end": {
                                              "line": 23,
                                              "column": 17
                                            }
                                          },
                                          "name": "orientation"
                                        },
                                        "property": {
                                          "type": "Literal",
                                          "start": 352,
                                          "end": 353,
                                          "loc": {
                                            "start": {
                                              "line": 23,
                                              "column": 18
                                            },
                                            "end": {
                                              "line": 23,
                                              "column": 19
                                            }
                                          },
                                          "value": 0,
                                          "rawValue": 0,
                                          "raw": "0"
                                        },
                                        "computed": true
                                      },
                                      "right": {
                                        "type": "BinaryExpression",
                                        "start": 358,
                                        "end": 417,
                                        "loc": {
                                          "start": {
                                            "line": 23,
                                            "column": 24
                                          },
                                          "end": {
                                            "line": 23,
                                            "column": 83
                                          }
                                        },
                                        "left": {
                                          "type": "BinaryExpression",
                                          "start": 359,
                                          "end": 397,
                                          "loc": {
                                            "start": {
                                              "line": 23,
                                              "column": 25
                                            },
                                            "end": {
                                              "line": 23,
                                              "column": 63
                                            }
                                          },
                                          "left": {
                                            "type": "BinaryExpression",
                                            "start": 359,
                                            "end": 394,
                                            "loc": {
                                              "start": {
                                                "line": 23,
                                                "column": 25
                                              },
                                              "end": {
                                                "line": 23,
                                                "column": 60
                                              }
                                            },
                                            "left": {
                                              "type": "ConditionalExpression",
                                              "start": 360,
                                              "end": 384,
                                              "loc": {
                                                "start": {
                                                  "line": 23,
                                                  "column": 26
                                                },
                                                "end": {
                                                  "line": 23,
                                                  "column": 50
                                                }
                                              },
                                              "test": {
                                                "type": "BinaryExpression",
                                                "start": 360,
                                                "end": 375,
                                                "loc": {
                                                  "start": {
                                                    "line": 23,
                                                    "column": 26
                                                  },
                                                  "end": {
                                                    "line": 23,
                                                    "column": 41
                                                  }
                                                },
                                                "left": {
                                                  "type": "Literal",
                                                  "start": 360,
                                                  "end": 365,
                                                  "loc": {
                                                    "start": {
                                                      "line": 23,
                                                      "column": 26
                                                    },
                                                    "end": {
                                                      "line": 23,
                                                      "column": 31
                                                    }
                                                  },
                                                  "value": false,
                                                  "rawValue": false,
                                                  "raw": "false"
                                                },
                                                "operator": "==",
                                                "right": {
                                                  "type": "Identifier",
                                                  "start": 369,
                                                  "end": 375,
                                                  "loc": {
                                                    "start": {
                                                      "line": 23,
                                                      "column": 35
                                                    },
                                                    "end": {
                                                      "line": 23,
                                                      "column": 41
                                                    }
                                                  },
                                                  "name": "invert"
                                                }
                                              },
                                              "consequent": {
                                                "type": "Literal",
                                                "start": 378,
                                                "end": 379,
                                                "loc": {
                                                  "start": {
                                                    "line": 23,
                                                    "column": 44
                                                  },
                                                  "end": {
                                                    "line": 23,
                                                    "column": 45
                                                  }
                                                },
                                                "value": 1,
                                                "rawValue": 1,
                                                "raw": "1"
                                              },
                                              "alternate": {
                                                "type": "UnaryExpression",
                                                "start": 382,
                                                "end": 384,
                                                "loc": {
                                                  "start": {
                                                    "line": 23,
                                                    "column": 48
                                                  },
                                                  "end": {
                                                    "line": 23,
                                                    "column": 50
                                                  }
                                                },
                                                "operator": "-",
                                                "prefix": true,
                                                "argument": {
                                                  "type": "Literal",
                                                  "start": 383,
                                                  "end": 384,
                                                  "loc": {
                                                    "start": {
                                                      "line": 23,
                                                      "column": 49
                                                    },
                                                    "end": {
                                                      "line": 23,
                                                      "column": 50
                                                    }
                                                  },
                                                  "value": 1,
                                                  "rawValue": 1,
                                                  "raw": "1"
                                                }
                                              },
                                              "parenthesizedExpression": true
                                            },
                                            "operator": "*",
                                            "right": {
                                              "type": "BinaryExpression",
                                              "start": 387,
                                              "end": 393,
                                              "loc": {
                                                "start": {
                                                  "line": 23,
                                                  "column": 53
                                                },
                                                "end": {
                                                  "line": 23,
                                                  "column": 59
                                                }
                                              },
                                              "left": {
                                                "type": "Literal",
                                                "start": 387,
                                                "end": 391,
                                                "loc": {
                                                  "start": {
                                                    "line": 23,
                                                    "column": 53
                                                  },
                                                  "end": {
                                                    "line": 23,
                                                    "column": 57
                                                  }
                                                },
                                                "value": 0.75,
                                                "rawValue": 0.75,
                                                "raw": "0.75"
                                              },
                                              "operator": "*",
                                              "right": {
                                                "type": "Identifier",
                                                "start": 392,
                                                "end": 393,
                                                "loc": {
                                                  "start": {
                                                    "line": 23,
                                                    "column": 58
                                                  },
                                                  "end": {
                                                    "line": 23,
                                                    "column": 59
                                                  }
                                                },
                                                "name": "z"
                                              },
                                              "parenthesizedExpression": true
                                            }
                                          },
                                          "operator": "*",
                                          "right": {
                                            "type": "Identifier",
                                            "start": 395,
                                            "end": 397,
                                            "loc": {
                                              "start": {
                                                "line": 23,
                                                "column": 61
                                              },
                                              "end": {
                                                "line": 23,
                                                "column": 63
                                              }
                                            },
                                            "name": "dy"
                                          },
                                          "parenthesizedExpression": true
                                        },
                                        "operator": "/",
                                        "right": {
                                          "type": "LogicalExpression",
                                          "start": 400,
                                          "end": 416,
                                          "loc": {
                                            "start": {
                                              "line": 23,
                                              "column": 66
                                            },
                                            "end": {
                                              "line": 23,
                                              "column": 82
                                            }
                                          },
                                          "left": {
                                            "type": "Identifier",
                                            "start": 400,
                                            "end": 408,
                                            "loc": {
                                              "start": {
                                                "line": 23,
                                                "column": 66
                                              },
                                              "end": {
                                                "line": 23,
                                                "column": 74
                                              }
                                            },
                                            "name": "friction"
                                          },
                                          "operator": "||",
                                          "right": {
                                            "type": "Literal",
                                            "start": 412,
                                            "end": 416,
                                            "loc": {
                                              "start": {
                                                "line": 23,
                                                "column": 78
                                              },
                                              "end": {
                                                "line": 23,
                                                "column": 82
                                              }
                                            },
                                            "value": 0.01,
                                            "rawValue": 0.01,
                                            "raw": "0.01"
                                          },
                                          "parenthesizedExpression": true
                                        }
                                      }
                                    }
                                  },
                                  {
                                    "type": "ExpressionStatement",
                                    "start": 424,
                                    "end": 494,
                                    "loc": {
                                      "start": {
                                        "line": 24,
                                        "column": 6
                                      },
                                      "end": {
                                        "line": 24,
                                        "column": 76
                                      }
                                    },
                                    "expression": {
                                      "type": "AssignmentExpression",
                                      "start": 424,
                                      "end": 494,
                                      "loc": {
                                        "start": {
                                          "line": 24,
                                          "column": 6
                                        },
                                        "end": {
                                          "line": 24,
                                          "column": 76
                                        }
                                      },
                                      "operator": "+=",
                                      "left": {
                                        "type": "MemberExpression",
                                        "start": 424,
                                        "end": 438,
                                        "loc": {
                                          "start": {
                                            "line": 24,
                                            "column": 6
                                          },
                                          "end": {
                                            "line": 24,
                                            "column": 20
                                          }
                                        },
                                        "object": {
                                          "type": "Identifier",
                                          "start": 424,
                                          "end": 435,
                                          "loc": {
                                            "start": {
                                              "line": 24,
                                              "column": 6
                                            },
                                            "end": {
                                              "line": 24,
                                              "column": 17
                                            }
                                          },
                                          "name": "orientation"
                                        },
                                        "property": {
                                          "type": "Literal",
                                          "start": 436,
                                          "end": 437,
                                          "loc": {
                                            "start": {
                                              "line": 24,
                                              "column": 18
                                            },
                                            "end": {
                                              "line": 24,
                                              "column": 19
                                            }
                                          },
                                          "value": 1,
                                          "rawValue": 1,
                                          "raw": "1"
                                        },
                                        "computed": true
                                      },
                                      "right": {
                                        "type": "BinaryExpression",
                                        "start": 442,
                                        "end": 494,
                                        "loc": {
                                          "start": {
                                            "line": 24,
                                            "column": 24
                                          },
                                          "end": {
                                            "line": 24,
                                            "column": 76
                                          }
                                        },
                                        "left": {
                                          "type": "BinaryExpression",
                                          "start": 443,
                                          "end": 474,
                                          "loc": {
                                            "start": {
                                              "line": 24,
                                              "column": 25
                                            },
                                            "end": {
                                              "line": 24,
                                              "column": 56
                                            }
                                          },
                                          "left": {
                                            "type": "BinaryExpression",
                                            "start": 443,
                                            "end": 471,
                                            "loc": {
                                              "start": {
                                                "line": 24,
                                                "column": 25
                                              },
                                              "end": {
                                                "line": 24,
                                                "column": 53
                                              }
                                            },
                                            "left": {
                                              "type": "ConditionalExpression",
                                              "start": 444,
                                              "end": 468,
                                              "loc": {
                                                "start": {
                                                  "line": 24,
                                                  "column": 26
                                                },
                                                "end": {
                                                  "line": 24,
                                                  "column": 50
                                                }
                                              },
                                              "test": {
                                                "type": "BinaryExpression",
                                                "start": 444,
                                                "end": 459,
                                                "loc": {
                                                  "start": {
                                                    "line": 24,
                                                    "column": 26
                                                  },
                                                  "end": {
                                                    "line": 24,
                                                    "column": 41
                                                  }
                                                },
                                                "left": {
                                                  "type": "Literal",
                                                  "start": 444,
                                                  "end": 449,
                                                  "loc": {
                                                    "start": {
                                                      "line": 24,
                                                      "column": 26
                                                    },
                                                    "end": {
                                                      "line": 24,
                                                      "column": 31
                                                    }
                                                  },
                                                  "value": false,
                                                  "rawValue": false,
                                                  "raw": "false"
                                                },
                                                "operator": "==",
                                                "right": {
                                                  "type": "Identifier",
                                                  "start": 453,
                                                  "end": 459,
                                                  "loc": {
                                                    "start": {
                                                      "line": 24,
                                                      "column": 35
                                                    },
                                                    "end": {
                                                      "line": 24,
                                                      "column": 41
                                                    }
                                                  },
                                                  "name": "invert"
                                                }
                                              },
                                              "consequent": {
                                                "type": "Literal",
                                                "start": 462,
                                                "end": 463,
                                                "loc": {
                                                  "start": {
                                                    "line": 24,
                                                    "column": 44
                                                  },
                                                  "end": {
                                                    "line": 24,
                                                    "column": 45
                                                  }
                                                },
                                                "value": 1,
                                                "rawValue": 1,
                                                "raw": "1"
                                              },
                                              "alternate": {
                                                "type": "UnaryExpression",
                                                "start": 466,
                                                "end": 468,
                                                "loc": {
                                                  "start": {
                                                    "line": 24,
                                                    "column": 48
                                                  },
                                                  "end": {
                                                    "line": 24,
                                                    "column": 50
                                                  }
                                                },
                                                "operator": "-",
                                                "prefix": true,
                                                "argument": {
                                                  "type": "Literal",
                                                  "start": 467,
                                                  "end": 468,
                                                  "loc": {
                                                    "start": {
                                                      "line": 24,
                                                      "column": 49
                                                    },
                                                    "end": {
                                                      "line": 24,
                                                      "column": 50
                                                    }
                                                  },
                                                  "value": 1,
                                                  "rawValue": 1,
                                                  "raw": "1"
                                                }
                                              },
                                              "parenthesizedExpression": true
                                            },
                                            "operator": "*",
                                            "right": {
                                              "type": "Identifier",
                                              "start": 470,
                                              "end": 471,
                                              "loc": {
                                                "start": {
                                                  "line": 24,
                                                  "column": 52
                                                },
                                                "end": {
                                                  "line": 24,
                                                  "column": 53
                                                }
                                              },
                                              "name": "z"
                                            }
                                          },
                                          "operator": "*",
                                          "right": {
                                            "type": "Identifier",
                                            "start": 472,
                                            "end": 474,
                                            "loc": {
                                              "start": {
                                                "line": 24,
                                                "column": 54
                                              },
                                              "end": {
                                                "line": 24,
                                                "column": 56
                                              }
                                            },
                                            "name": "dx"
                                          },
                                          "parenthesizedExpression": true
                                        },
                                        "operator": "/",
                                        "right": {
                                          "type": "LogicalExpression",
                                          "start": 477,
                                          "end": 493,
                                          "loc": {
                                            "start": {
                                              "line": 24,
                                              "column": 59
                                            },
                                            "end": {
                                              "line": 24,
                                              "column": 75
                                            }
                                          },
                                          "left": {
                                            "type": "Identifier",
                                            "start": 477,
                                            "end": 485,
                                            "loc": {
                                              "start": {
                                                "line": 24,
                                                "column": 59
                                              },
                                              "end": {
                                                "line": 24,
                                                "column": 67
                                              }
                                            },
                                            "name": "friction"
                                          },
                                          "operator": "||",
                                          "right": {
                                            "type": "Literal",
                                            "start": 489,
                                            "end": 493,
                                            "loc": {
                                              "start": {
                                                "line": 24,
                                                "column": 71
                                              },
                                              "end": {
                                                "line": 24,
                                                "column": 75
                                              }
                                            },
                                            "value": 0.01,
                                            "rawValue": 0.01,
                                            "raw": "0.01"
                                          },
                                          "parenthesizedExpression": true
                                        }
                                      }
                                    }
                                  }
                                ]
                              },
                              "alternate": null
                            }
                          ]
                        }
                      }
                    ]
                  }
                }
              ]
            }
          }
        }
      }
    }
  ]
}